importtime_convert/__init__.py
importtime_convert/__main__.py
importtime_convert/_output_formats.py
importtime_convert/_parse.py
importtime_convert/py.typed
importtime_convert-1.1.0.dist-info/licenses/LICENSE.txt
importtime_convert-1.1.0.dist-info/METADATA
importtime_convert-1.1.0.dist-info/WHEEL
importtime_convert-1.1.0.dist-info/entry_points.txt
importtime_convert-1.1.0.dist-info/top_level.txt
importtime_convert-1.1.0.dist-info/RECORD
