Metadata-Version: 2.4
Name: importtime_convert
Version: 1.1.0
Summary: Parse the output of `python -X importtime` and convert it to other formats.
Author-email: Max Marrone <max@marrone.nyc>
Project-URL: Source, https://github.com/SyntaxColoring/importtime_convert
Project-URL: Issues, https://github.com/SyntaxColoring/importtime_convert/issues
Project-URL: Changelog, https://github.com/SyntaxColoring/importtime_convert/blob/main/CHANGELOG.md
Classifier: Development Status :: 5 - Production/Stable
Classifier: License :: OSI Approved :: MIT License
Classifier: Programming Language :: Python :: 3
Classifier: Typing :: Typed
Requires-Python: >=3.9
License-File: LICENSE.txt
Dynamic: license-file
